LICENSE
MANIFEST.in
README.md
requirements.txt
setup.py
bin/extratools-flatten
bin/extratools-remap
bin/extratools-teststats
extratools/__common.py
extratools/__init__.py
extratools/__join.py
extratools/debugtools.py
extratools/defaultlist.py
extratools/dicttools.py
extratools/disjointsets.py
extratools/gittools.py
extratools/graphtools.py
extratools/htmltools.py
extratools/jsontools.py
extratools/mathtools.py
extratools/misctools.py
extratools/printtools.py
extratools/rangetools.py
extratools/recttools.py
extratools/segmenttree.py
extratools/seqtools.py
extratools/settools.py
extratools/sortedtools.py
extratools/stattools.py
extratools/strtools.py
extratools/tabletools.py
extratools.egg-info/PKG-INFO
extratools.egg-info/SOURCES.txt
extratools.egg-info/dependency_links.txt
extratools.egg-info/requires.txt
extratools.egg-info/top_level.txt
extratools/htmltools/emmet.js