Metadata-Version: 2.1
Name: extratools
Version: 0.8.1
Summary: 145+ extra higher-level functional tools beyond standard and third-Party libraries.
Home-page: https://github.com/chuanconggao/extratools
Author: Chuancong Gao
Author-email: chuancong@gmail.com
License: MIT
Download-URL: https://github.com/chuanconggao/extratools/tarball/0.8.1
Keywords: functional,tools
Platform: UNKNOWN
Classifier: Operating System :: OS Independent
Classifier: Programming Language :: Python
Classifier: Programming Language :: Python :: 3
Requires-Python: >= 3
